unencryptedsocket2/__init__.py
unencryptedsocket2/server.py
unencryptedsocket2/utils.py
unencryptedsocket2/__metadata__/DISCLIAIMER.md
unencryptedsocket2/__metadata__/LICENSE
unencryptedsocket2/__metadata__/README.md
unencryptedsocket2/__metadata__/__init__.py
unencryptedsocket2/__metadata__/requirements.txt
unencryptedsocket2-0.0.3.dist-info/LICENSE
unencryptedsocket2-0.0.3.dist-info/METADATA
unencryptedsocket2-0.0.3.dist-info/WHEEL
unencryptedsocket2-0.0.3.dist-info/top_level.txt
unencryptedsocket2-0.0.3.dist-info/RECORD
